autogoal_transformers/__init__.py
autogoal_transformers/_bert.py
autogoal_transformers/_builder.py
autogoal_transformers/_generated.py
autogoal_transformers/_manual.py
autogoal_transformers/_tc_generated.py
autogoal_transformers/_utils.py
autogoal_transformers/download_tec.py
autogoal_transformers/download_toc.py
autogoal_transformers/test.py
autogoal_transformers/version.txt
autogoal_transformers-0.8.4.dist-info/WHEEL
autogoal_transformers-0.8.4.dist-info/METADATA
autogoal_transformers-0.8.4.dist-info/RECORD
