Metadata-Version: 2.1
Name: autogoal-transformers
Version: 0.8.4
Summary: transformers algorithm library wrapper for AutoGOAL
Home-page: https://autogoal.github.io
License: MIT
Author: Suilan Estevez-Velarde
Author-email: suilanestevez@gmail.com
Requires-Python: >=3.9.13,<3.11
Classifier: License :: OSI Approved :: MIT License
Classifier: Programming Language :: Python :: 3
Classifier: Programming Language :: Python :: 3.10
Requires-Dist: autogoal (>=1.0.2,<2.0.0)
Requires-Dist: autogoal-contrib (>=0.8.2,<0.9.0)
Requires-Dist: datasets (>=2.14.6,<3.0.0)
Requires-Dist: evaluate (>=0.4.1,<0.5.0)
Requires-Dist: torch (>=2.0.0,<3.0.0)
Requires-Dist: transformers (>=4.27.3,<5.0.0)
Project-URL: Documentation, https://autogoal.github.io
Project-URL: Repository, https://github.com/autogoal/autogoal-contrib
